setup.mongo.py
ma.mongo.egg-info/PKG-INFO
ma.mongo.egg-info/SOURCES.txt
ma.mongo.egg-info/dependency_links.txt
ma.mongo.egg-info/top_level.txt
ma/mongo/__init__.py
ma/mongo/lock.py
ma/mongo/log.py
ma/mongo/validate.py