Metadata-Version: 1.0
Name: ma.mongo
Version: 1.0.1
Summary: MongoDB utilities
Home-page: UNKNOWN
Author: Fredrik Haard
Author-email: fredrik@metallapan.se
License: UNKNOWN
Platform: UNKNOWN
